[
  {
    "text": "외주 작업자 근로계약서\n",
    "chunk_length": 13,
    "type": "제목",
    "content_labels": [
      "기타"
    ],
    "document_title": "근로계약서_0009",
    "document_type": "계약 법률 문서",
    "document_date": "2024-10-17",
    "document_category": "고용계약",
    "related_law": "근로기준법, 저작권법, 민법",
    "document_purpose": "외주 작업자와 프리랜서 근로계약을 체결하여 근로조건, 권리, 의무를 명확히 규정하고, 계약 이행을 보장하기 위함",
    "document_use_case": "출판, 번역, 콘텐츠 제작 등 외주 작업을 의뢰할 때 활용. 특히 출판물의 번역 작업을 프리랜서에게 의뢰할 때 사용됨.",
    "public_domain_sources": null
  },
  {
    "text": "(@회사명) (이하 “갑”이라 한다)는 (@성명1)(이하 “을”이라 한다)에게 (@담당 업무)를 의뢰하면서 다음과 같이 `프리랜서 근로계약`을 체결하고, 이를 이행할 것을 약정한다.\n",
    "chunk_length": 102,
    "type": "서문",
    "content_labels": [
      "계약의 당사자"
    ],
    "document_title": "근로계약서_0009",
    "document_type": "계약 법률 문서",
    "document_date": "2024-10-17",
    "document_category": "고용계약",
    "related_law": "근로기준법, 저작권법, 민법",
    "document_purpose": "외주 작업자와 프리랜서 근로계약을 체결하여 근로조건, 권리, 의무를 명확히 규정하고, 계약 이행을 보장하기 위함",
    "document_use_case": "출판, 번역, 콘텐츠 제작 등 외주 작업을 의뢰할 때 활용. 특히 출판물의 번역 작업을 프리랜서에게 의뢰할 때 사용됨.",
    "public_domain_sources": null
  },
  {
    "text": "제7조(계약의 해지)",
    "chunk_length": 11,
    "type": "본문",
    "content_labels": [
      "근로계약의 종료"
    ],
    "document_title": "근로계약서_0009",
    "document_type": "계약 법률 문서",
    "document_date": "2024-10-17",
    "document_category": "고용계약",
    "related_law": "근로기준법, 저작권법, 민법",
    "document_purpose": "외주 작업자와 프리랜서 근로계약을 체결하여 근로조건, 권리, 의무를 명확히 규정하고, 계약 이행을 보장하기 위함",
    "document_use_case": "출판, 번역, 콘텐츠 제작 등 외주 작업을 의뢰할 때 활용. 특히 출판물의 번역 작업을 프리랜서에게 의뢰할 때 사용됨.",
    "public_domain_sources": null
  },
  {
    "text": "① “갑”과 “을”은 불가피한 이유에 의하여 계약기간 중에 본 계약을 해지하고자 할 때는 계약만료 1개월 전에 서면으로서 상대방에게 통지하여야 한다.",
    "chunk_length": 83,
    "type": "본문",
    "content_labels": [
      "퇴직 절차"
    ],
    "document_title": "근로계약서_0009",
    "document_type": "계약 법률 문서",
    "document_date": "2024-10-17",
    "document_category": "고용계약",
    "related_law": "근로기준법, 저작권법, 민법",
    "document_purpose": "외주 작업자와 프리랜서 근로계약을 체결하여 근로조건, 권리, 의무를 명확히 규정하고, 계약 이행을 보장하기 위함",
    "document_use_case": "출판, 번역, 콘텐츠 제작 등 외주 작업을 의뢰할 때 활용. 특히 출판물의 번역 작업을 프리랜서에게 의뢰할 때 사용됨.",
    "public_domain_sources": null
  },
  {
    "text": "② “갑”과 “을”은 상당한 계약위반이나 기타의 사정에 의하여 계약업무 이행에 중대한 지장이 생긴 경우에는 전항의 규정에도 불구하고 통지 후 즉시 계약을 해지할 수 있다.\n",
    "chunk_length": 96,
    "type": "본문",
    "content_labels": [
      "근로계약의 종료"
    ],
    "document_title": "근로계약서_0009",
    "document_type": "계약 법률 문서",
    "document_date": "2024-10-17",
    "document_category": "고용계약",
    "related_law": "근로기준법, 저작권법, 민법",
    "document_purpose": "외주 작업자와 프리랜서 근로계약을 체결하여 근로조건, 권리, 의무를 명확히 규정하고, 계약 이행을 보장하기 위함",
    "document_use_case": "출판, 번역, 콘텐츠 제작 등 외주 작업을 의뢰할 때 활용. 특히 출판물의 번역 작업을 프리랜서에게 의뢰할 때 사용됨.",
    "public_domain_sources": null
  },
  {
    "text": "③ ‘갑’과 ‘을’은 계약내용을 변경할 필요가 있을 때에는 상호협의를 통해 변경한 내용을 특약의 형식으로 정할 수 있다.\n",
    "chunk_length": 68,
    "type": "본문",
    "content_labels": [
      "근로 환경 변경"
    ],
    "document_title": "근로계약서_0009",
    "document_type": "계약 법률 문서",
    "document_date": "2024-10-17",
    "document_category": "고용계약",
    "related_law": "근로기준법, 저작권법, 민법",
    "document_purpose": "외주 작업자와 프리랜서 근로계약을 체결하여 근로조건, 권리, 의무를 명확히 규정하고, 계약 이행을 보장하기 위함",
    "document_use_case": "출판, 번역, 콘텐츠 제작 등 외주 작업을 의뢰할 때 활용. 특히 출판물의 번역 작업을 프리랜서에게 의뢰할 때 사용됨.",
    "public_domain_sources": null
  },
  {
    "text": "2019년   02월   07일",
    "chunk_length": 17,
    "type": "날짜",
    "content_labels": [
      "계약 체결 일자"
    ],
    "document_title": "근로계약서_0009",
    "document_type": "계약 법률 문서",
    "document_date": "2024-10-17",
    "document_category": "고용계약",
    "related_law": "근로기준법, 저작권법, 민법",
    "document_purpose": "외주 작업자와 프리랜서 근로계약을 체결하여 근로조건, 권리, 의무를 명확히 규정하고, 계약 이행을 보장하기 위함",
    "document_use_case": "출판, 번역, 콘텐츠 제작 등 외주 작업을 의뢰할 때 활용. 특히 출판물의 번역 작업을 프리랜서에게 의뢰할 때 사용됨.",
    "public_domain_sources": null
  },
  {
    "text": "「갑」\n주 소 : (@주소1)\n회사명 : (@회사명)\n대리인 : (@성명2) (인)\n",
    "chunk_length": 47,
    "type": "기명날인",
    "content_labels": [
      "사용자의 인적사항",
      "사용자의 기명날인"
    ],
    "document_title": "근로계약서_0009",
    "document_type": "계약 법률 문서",
    "document_date": "2024-10-17",
    "document_category": "고용계약",
    "related_law": "근로기준법, 저작권법, 민법",
    "document_purpose": "외주 작업자와 프리랜서 근로계약을 체결하여 근로조건, 권리, 의무를 명확히 규정하고, 계약 이행을 보장하기 위함",
    "document_use_case": "출판, 번역, 콘텐츠 제작 등 외주 작업을 의뢰할 때 활용. 특히 출판물의 번역 작업을 프리랜서에게 의뢰할 때 사용됨.",
    "public_domain_sources": null
  },
  {
    "text": "「을」\n주민번호 : (@주민번호)\n연락처 : (@전화번호)\n주소 : (@주소2)\n성 명 : (@성명1) (인)\n",
    "chunk_length": 62,
    "type": "기명날인",
    "content_labels": [
      "근로자의 인적사항",
      "근로자의 기명날인"
    ],
    "document_title": "근로계약서_0009",
    "document_type": "계약 법률 문서",
    "document_date": "2024-10-17",
    "document_category": "고용계약",
    "related_law": "근로기준법, 저작권법, 민법",
    "document_purpose": "외주 작업자와 프리랜서 근로계약을 체결하여 근로조건, 권리, 의무를 명확히 규정하고, 계약 이행을 보장하기 위함",
    "document_use_case": "출판, 번역, 콘텐츠 제작 등 외주 작업을 의뢰할 때 활용. 특히 출판물의 번역 작업을 프리랜서에게 의뢰할 때 사용됨.",
    "public_domain_sources": null
  },
  {
    "text": "제1조(계약의 목적)\n\n본 계약은 “갑”이 “을”에게 (@담당 업무)를 의뢰함에 있어 필요한 제반 사항을 정함을 그 목적으로 한다.",
    "article_number": 1,
    "article_title": "제1조(계약의 목적)\n",
    "chunk_part": 1,
    "total_parts": 1,
    "chunk_length": 73,
    "items_count": 1,
    "type": "article",
    "content_labels": [
      "계약의 목적"
    ],
    "document_title": "근로계약서_0009",
    "document_type": "계약 법률 문서",
    "document_date": "2024-10-17",
    "document_category": "고용계약",
    "related_law": "근로기준법, 저작권법, 민법",
    "document_purpose": "외주 작업자와 프리랜서 근로계약을 체결하여 근로조건, 권리, 의무를 명확히 규정하고, 계약 이행을 보장하기 위함",
    "document_use_case": "출판, 번역, 콘텐츠 제작 등 외주 작업을 의뢰할 때 활용. 특히 출판물의 번역 작업을 프리랜서에게 의뢰할 때 사용됨.",
    "public_domain_sources": null
  },
  {
    "text": "제2조(계약의 범위)\n\"을\"은 \"갑\"이 의뢰한 다음 호의 작업내용을 수행하여야 한다.\n① 작업1(번역)",
    "article_number": 2,
    "article_title": "제2조(계약의 범위)",
    "chunk_part": 1,
    "total_parts": 1,
    "chunk_length": 57,
    "items_count": 2,
    "type": "article",
    "content_labels": [
      "담당 업무"
    ],
    "document_title": "근로계약서_0009",
    "document_type": "계약 법률 문서",
    "document_date": "2024-10-17",
    "document_category": "고용계약",
    "related_law": "근로기준법, 저작권법, 민법",
    "document_purpose": "외주 작업자와 프리랜서 근로계약을 체결하여 근로조건, 권리, 의무를 명확히 규정하고, 계약 이행을 보장하기 위함",
    "document_use_case": "출판, 번역, 콘텐츠 제작 등 외주 작업을 의뢰할 때 활용. 특히 출판물의 번역 작업을 프리랜서에게 의뢰할 때 사용됨.",
    "public_domain_sources": null
  },
  {
    "text": "제3조(계약기간 및 계약금액)\n\n① 본 계약의 계약기간은 2019년 2월 8일부터 2019년 3월 31일까지로 한다.\n\n② 총 계약금액은 세금 차감 후 금액으로 산정하며, “갑”은 “을”에게 (@금액)을 지급한다\n\n③ 대금지급은 작업 완료일을 시점으로 15일 안에 지급하는 것으로 하며, 총 번역비에서 계약금을 제한 금액을 “을”이 정한 (@계좌번호)으로 입금한다.\n",
    "article_number": 3,
    "article_title": "제3조(계약기간 및 계약금액)\n",
    "chunk_part": 1,
    "total_parts": 1,
    "chunk_length": 205,
    "items_count": 3,
    "type": "article",
    "content_labels": [
      "근로 계약 기간",
      "임금액"
    ],
    "document_title": "근로계약서_0009",
    "document_type": "계약 법률 문서",
    "document_date": "2024-10-17",
    "document_category": "고용계약",
    "related_law": "근로기준법, 저작권법, 민법",
    "document_purpose": "외주 작업자와 프리랜서 근로계약을 체결하여 근로조건, 권리, 의무를 명확히 규정하고, 계약 이행을 보장하기 위함",
    "document_use_case": "출판, 번역, 콘텐츠 제작 등 외주 작업을 의뢰할 때 활용. 특히 출판물의 번역 작업을 프리랜서에게 의뢰할 때 사용됨.",
    "public_domain_sources": null
  },
  {
    "text": "제4조(납품 및 양도)\n\n① “을”은 작업 진행 중 중간 완료된 성과물을 2019년 2월 28일까지 “갑”에게 납품하기로 하며 최종 작업본은 검토 및 수정 후 계약 완료일인 2019년 3월 31일까지 완성품으로 납품키로 한다. 만약 완성품의 수정 및 보완이 필요한 경우에는 “을”과 일정을 협의하여 진행키로 한다.\n\n② “을”은 출간 직전에 ”갑”과 저작재산권 양도 계약을 맺고 위 저작물에 대한 저작재산권 전부와 위 저작물을 원저작물로 하는 2차적 저작물 또는 위 저작물을 구성부분으로 하는 편집저작물을 작성하여 이용할 권리 전부를 ”갑”에게 양도한다.\n",
    "article_number": 4,
    "article_title": "제4조(납품 및 양도)\n",
    "chunk_part": 1,
    "total_parts": 1,
    "chunk_length": 311,
    "items_count": 2,
    "type": "article",
    "content_labels": [
      "담당 업무"
    ],
    "document_title": "근로계약서_0009",
    "document_type": "계약 법률 문서",
    "document_date": "2024-10-17",
    "document_category": "고용계약",
    "related_law": "근로기준법, 저작권법, 민법",
    "document_purpose": "외주 작업자와 프리랜서 근로계약을 체결하여 근로조건, 권리, 의무를 명확히 규정하고, 계약 이행을 보장하기 위함",
    "document_use_case": "출판, 번역, 콘텐츠 제작 등 외주 작업을 의뢰할 때 활용. 특히 출판물의 번역 작업을 프리랜서에게 의뢰할 때 사용됨.",
    "public_domain_sources": null
  },
  {
    "text": "제5조(협조의무)\n\n“갑”은 “을”이 작업하는 데 필요한 자료 및 정보 등을 제공하여야 하며, 작업수행을 위한 “을”의 요청이 있는 경우 이에 적극적으로 협조하여야 한다.\n",
    "article_number": 5,
    "article_title": "제5조(협조의무)\n",
    "chunk_part": 1,
    "total_parts": 1,
    "chunk_length": 96,
    "items_count": 1,
    "type": "article",
    "content_labels": [
      "기타"
    ],
    "document_title": "근로계약서_0009",
    "document_type": "계약 법률 문서",
    "document_date": "2024-10-17",
    "document_category": "고용계약",
    "related_law": "근로기준법, 저작권법, 민법",
    "document_purpose": "외주 작업자와 프리랜서 근로계약을 체결하여 근로조건, 권리, 의무를 명확히 규정하고, 계약 이행을 보장하기 위함",
    "document_use_case": "출판, 번역, 콘텐츠 제작 등 외주 작업을 의뢰할 때 활용. 특히 출판물의 번역 작업을 프리랜서에게 의뢰할 때 사용됨.",
    "public_domain_sources": null
  },
  {
    "text": "제6조(비밀유지)\n“을”은 본 작업과 관련하여 지득한 일체의 정보를 외부에 누설하거나 유출해서는 안되며, 이로 인해 발생되는 손해에 대해 책임을 지기로 한다.\n",
    "article_number": 6,
    "article_title": "제6조(비밀유지)",
    "chunk_part": 1,
    "total_parts": 1,
    "chunk_length": 89,
    "items_count": 1,
    "type": "article",
    "content_labels": [
      "비밀 유지 의무"
    ],
    "document_title": "근로계약서_0009",
    "document_type": "계약 법률 문서",
    "document_date": "2024-10-17",
    "document_category": "고용계약",
    "related_law": "근로기준법, 저작권법, 민법",
    "document_purpose": "외주 작업자와 프리랜서 근로계약을 체결하여 근로조건, 권리, 의무를 명확히 규정하고, 계약 이행을 보장하기 위함",
    "document_use_case": "출판, 번역, 콘텐츠 제작 등 외주 작업을 의뢰할 때 활용. 특히 출판물의 번역 작업을 프리랜서에게 의뢰할 때 사용됨.",
    "public_domain_sources": null
  },
  {
    "text": "제8조(손해배상)\n‘을’은 본 계약과 관련하여 ‘을’의 귀책사유로 인해 ‘갑’에게 손해를 입힌 경우 손해액을 배상하여야 한다. 다만, 천재지변 등 불가항력적인 경우에는 그러하지 아니하다.",
    "article_number": 8,
    "article_title": "제8조(손해배상)",
    "chunk_part": 1,
    "total_parts": 1,
    "chunk_length": 104,
    "items_count": 1,
    "type": "article",
    "content_labels": [
      "손해배상의 예정"
    ],
    "document_title": "근로계약서_0009",
    "document_type": "계약 법률 문서",
    "document_date": "2024-10-17",
    "document_category": "고용계약",
    "related_law": "근로기준법, 저작권법, 민법",
    "document_purpose": "외주 작업자와 프리랜서 근로계약을 체결하여 근로조건, 권리, 의무를 명확히 규정하고, 계약 이행을 보장하기 위함",
    "document_use_case": "출판, 번역, 콘텐츠 제작 등 외주 작업을 의뢰할 때 활용. 특히 출판물의 번역 작업을 프리랜서에게 의뢰할 때 사용됨.",
    "public_domain_sources": null
  },
  {
    "text": "제9조(해석)\n본 계약에 명기하지 아니한 사항 및 본 계약의 해석상의 이의가 있을 때에는 쌍방의 협의 하에 결정하기로 한다.",
    "article_number": 9,
    "article_title": "제9조(해석)",
    "chunk_part": 1,
    "total_parts": 1,
    "chunk_length": 69,
    "items_count": 1,
    "type": "article",
    "content_labels": [
      "기타"
    ],
    "document_title": "근로계약서_0009",
    "document_type": "계약 법률 문서",
    "document_date": "2024-10-17",
    "document_category": "고용계약",
    "related_law": "근로기준법, 저작권법, 민법",
    "document_purpose": "외주 작업자와 프리랜서 근로계약을 체결하여 근로조건, 권리, 의무를 명확히 규정하고, 계약 이행을 보장하기 위함",
    "document_use_case": "출판, 번역, 콘텐츠 제작 등 외주 작업을 의뢰할 때 활용. 특히 출판물의 번역 작업을 프리랜서에게 의뢰할 때 사용됨.",
    "public_domain_sources": null
  },
  {
    "text": "제10조(소송관할)\n본 계약으로 발생되는 분쟁은 서울중앙지방법원을 관할법원으로 한다.",
    "article_number": 10,
    "article_title": "제10조(소송관할)",
    "chunk_part": 1,
    "total_parts": 1,
    "chunk_length": 47,
    "items_count": 1,
    "type": "article",
    "content_labels": [
      "관할법원"
    ],
    "document_title": "근로계약서_0009",
    "document_type": "계약 법률 문서",
    "document_date": "2024-10-17",
    "document_category": "고용계약",
    "related_law": "근로기준법, 저작권법, 민법",
    "document_purpose": "외주 작업자와 프리랜서 근로계약을 체결하여 근로조건, 권리, 의무를 명확히 규정하고, 계약 이행을 보장하기 위함",
    "document_use_case": "출판, 번역, 콘텐츠 제작 등 외주 작업을 의뢰할 때 활용. 특히 출판물의 번역 작업을 프리랜서에게 의뢰할 때 사용됨.",
    "public_domain_sources": null
  }
]